{"assets":{"0CD95CC1CF4C2220331C592C5636D02A":{"type":"texture","index":1,"assetRequest":{"type":"slide","state":"incoming","slide":"C13480DD-5E7F-4404-8749-5C488103A479"},"url":{"web":"assets/22E32216-62F0-4DB0-9AE0-9F7FDA8C90FB.svgmap"},"width":1024,"height":768},"A93C9E9D0F63C1DD7C024F0BD2BB285D":{"type":"texture","index":0,"assetRequest":{"type":"slide","state":"outgoing","slide":"22E32216-62F0-4DB0-9AE0-9F7FDA8C90FB"},"url":{"web":"assets/22E32216-62F0-4DB0-9AE0-9F7FDA8C90FB.svgmap"},"width":1024,"height":768}},"events":[{"effects":[{"beginTime":0,"baseLayer":{"animations":[],"initialState":{"affineTransform":[1,0,0,1,0,0],"masksToBounds":false,"rotation":0,"scale":1,"position":{"pointX":512,"pointY":384},"width":1024,"sublayerTransform":[1,0,0,0,0,1,0,0,0,0,1,0,0,0,0,1],"contentsRect":{"y":0,"x":0,"width":1,"height":1},"opacity":1,"edgeAntialiasingMask":251658240,"height":768,"hidden":false,"anchorPoint":{"pointX":0.5,"pointY":0.5}},"objectID":"0","layers":[{"animations":[],"initialState":{"affineTransform":[1,0,0,1,0,0],"masksToBounds":false,"rotation":0,"scale":1,"position":{"pointX":512,"pointY":384},"width":1024,"sublayerTransform":[1,0,0,0,0,1,0,0,0,0,1,-0.0004922987690640373,0,0,0,1],"contentsRect":{"y":0,"x":0,"width":1,"height":1},"opacity":1,"edgeAntialiasingMask":251658240,"height":768,"hidden":false,"anchorPoint":{"pointX":0.5,"pointY":0.5}},"layers":[{"animations":[],"layers":[],"texturedRectangle":{"isBackgroundTexture":false,"singleTextureOpacity":1,"textureType":0,"textBaseline":0,"textXHeight":0,"isVerticalText":false},"initialState":{"affineTransform":[1,0,0,1,0,0],"masksToBounds":false,"rotation":0,"scale":1,"position":{"pointX":512,"pointY":384},"width":1024,"sublayerTransform":[1,0,0,0,0,1,0,0,0,0,1,0,0,0,0,1],"contentsRect":{"y":0,"x":0,"width":1,"height":1},"opacity":1,"edgeAntialiasingMask":0,"height":768,"hidden":false,"anchorPoint":{"pointX":0.5,"pointY":0.5}},"texture":"0CD95CC1CF4C2220331C592C5636D02A"},{"animations":[{"timeOffset":0,"from":{"scalar":false},"beginTime":0,"repeatCount":0,"fillMode":"both","property":"hidden","autoreverses":false,"duration":0.01,"to":{"scalar":true}}],"layers":[],"texturedRectangle":{"isBackgroundTexture":false,"singleTextureOpacity":1,"textureType":0,"textBaseline":0,"textXHeight":0,"isVerticalText":false},"initialState":{"affineTransform":[1,0,0,1,0,0],"masksToBounds":false,"rotation":0,"scale":1,"position":{"pointX":512,"pointY":384},"width":1024,"sublayerTransform":[1,0,0,0,0,1,0,0,0,0,1,0,0,0,0,1],"contentsRect":{"y":0,"x":0,"width":1,"height":1},"opacity":1,"edgeAntialiasingMask":0,"height":768,"hidden":false,"anchorPoint":{"pointX":0.5,"pointY":0.5}},"texture":"A93C9E9D0F63C1DD7C024F0BD2BB285D"}]}]},"effects":[],"duration":0.01,"type":"transition","name":"none","objectID":"0"}],"automaticPlay":false,"hyperlinks":[],"accessibility":[{"text":"lib.png","targetRectangle":{"y":32.21875,"x":529,"width":420,"height":703.5625}},{"text":"Interesting because of:","targetRectangle":{"y":186.3671875,"x":92.67999900272912,"width":241.4328,"height":28}},{"text":"interactions","targetRectangle":{"y":214.3671875,"x":119.6799990027291,"width":121.57488,"height":54.8799991607666}},{"text":"real-world analogues","targetRectangle":{"y":269.2471866607666,"x":119.6799990027291,"width":220.4529600000001,"height":54.8799991607666}},{"text":"similarity to real systems","targetRectangle":{"y":324.1271858215332,"x":119.6799990027291,"width":255.70944,"height":54.8799991607666}},{"text":"The library is a repository of books","targetRectangle":{"y":379.0071849822998,"x":92.67999900272912,"width":362.46672,"height":54.8799991607666}},{"text":"It has patrons","targetRectangle":{"y":433.8871841430664,"x":92.67999900272912,"width":143.37792,"height":54.8799991607666}},{"text":"A patron checks a book in and out","targetRectangle":{"y":488.767183303833,"x":92.67999900272912,"width":361.7140799999999,"height":54.8799991607666}},{"text":"Patrons know what they’ve check out","targetRectangle":{"y":543.6471824645996,"x":92.67999900272912,"width":387.8447999999999,"height":54.8799991607666}},{"text":"Books and patrons have relevant information","targetRectangle":{"y":598.5271816253662,"x":92.67999900272912,"width":352.11792,"height":82.8799991607666}},{"text":"Library: OOP","targetRectangle":{"y":58,"x":55.9647961853027,"width":440.0704000000001,"height":90}}],"baseLayer":{"animations":[],"initialState":{"affineTransform":[1,0,0,1,0,0],"masksToBounds":false,"rotation":0,"scale":1,"position":{"pointX":512,"pointY":384},"width":1024,"sublayerTransform":[1,0,0,0,0,1,0,0,0,0,1,0,0,0,0,1],"contentsRect":{"y":0,"x":0,"width":1,"height":1},"opacity":1,"edgeAntialiasingMask":251658240,"height":768,"hidden":false,"anchorPoint":{"pointX":0.5,"pointY":0.5}},"objectID":"0","layers":[{"animations":[],"initialState":{"affineTransform":[1,0,0,1,0,0],"masksToBounds":false,"rotation":0,"scale":1,"position":{"pointX":512,"pointY":384},"width":1024,"sublayerTransform":[1,0,0,0,0,1,0,0,0,0,1,-0.0004922987690640373,0,0,0,1],"contentsRect":{"y":0,"x":0,"width":1,"height":1},"opacity":1,"edgeAntialiasingMask":251658240,"height":768,"hidden":false,"anchorPoint":{"pointX":0.5,"pointY":0.5}},"layers":[{"animations":[],"layers":[],"texturedRectangle":{"isBackgroundTexture":false,"singleTextureOpacity":1,"textureType":0,"textBaseline":0,"textXHeight":0,"isVerticalText":false},"initialState":{"affineTransform":[1,0,0,1,0,0],"masksToBounds":false,"rotation":0,"scale":1,"position":{"pointX":512,"pointY":384},"width":1024,"sublayerTransform":[1,0,0,0,0,1,0,0,0,0,1,0,0,0,0,1],"contentsRect":{"y":0,"x":0,"width":1,"height":1},"opacity":1,"edgeAntialiasingMask":0,"height":768,"hidden":false,"anchorPoint":{"pointX":0.5,"pointY":0.5}},"texture":"A93C9E9D0F63C1DD7C024F0BD2BB285D"}]}]}}]}