{"assets":{"8A306DEF3FA436E38BCC5CFB45ACBC59":{"type":"texture","index":67,"assetRequest":{"type":"slide","state":"incoming","slide":"1DE4F9DB-135E-4DF3-9043-B0335AB23959"},"url":{"web":"assets/8A306DEF3FA436E38BCC5CFB45ACBC59.svg"},"width":1024,"height":768},"03B001ED4B040174678FD2FC47A129FE":{"type":"texture","index":66,"assetRequest":{"type":"slide","state":"outgoing","slide":"CEDCE41C-B704-4CB3-92A4-05DAE4FFFD5D"},"url":{"web":"assets/03B001ED4B040174678FD2FC47A129FE.svg"},"width":1024,"height":768}},"events":[{"effects":[{"beginTime":0,"baseLayer":{"animations":[],"initialState":{"affineTransform":[1,0,0,1,0,0],"masksToBounds":false,"rotation":0,"scale":1,"position":{"pointX":512,"pointY":384},"width":1024,"sublayerTransform":[1,0,0,0,0,1,0,0,0,0,1,0,0,0,0,1],"contentsRect":{"y":0,"x":0,"width":1,"height":1},"opacity":1,"edgeAntialiasingMask":251658240,"height":768,"hidden":false,"anchorPoint":{"pointX":0.5,"pointY":0.5}},"objectID":"0","layers":[{"animations":[],"initialState":{"affineTransform":[1,0,0,1,0,0],"masksToBounds":false,"rotation":0,"scale":1,"position":{"pointX":512,"pointY":384},"width":1024,"sublayerTransform":[1,0,0,0,0,1,0,0,0,0,1,-0.0004922987690640373,0,0,0,1],"contentsRect":{"y":0,"x":0,"width":1,"height":1},"opacity":1,"edgeAntialiasingMask":251658240,"height":768,"hidden":false,"anchorPoint":{"pointX":0.5,"pointY":0.5}},"layers":[{"animations":[],"layers":[],"initialState":{"affineTransform":[1,0,0,1,0,0],"masksToBounds":false,"rotation":0,"scale":1,"position":{"pointX":512,"pointY":384},"width":1024,"sublayerTransform":[1,0,0,0,0,1,0,0,0,0,1,0,0,0,0,1],"contentsRect":{"y":0,"x":0,"width":1,"height":1},"opacity":1,"edgeAntialiasingMask":0,"height":768,"hidden":false,"anchorPoint":{"pointX":0.5,"pointY":0.5}},"texture":"8A306DEF3FA436E38BCC5CFB45ACBC59"},{"animations":[{"timeOffset":0,"from":{"scalar":false},"beginTime":0,"repeatCount":0,"fillMode":"both","property":"hidden","autoreverses":false,"duration":0.01,"to":{"scalar":true}}],"layers":[],"initialState":{"affineTransform":[1,0,0,1,0,0],"masksToBounds":false,"rotation":0,"scale":1,"position":{"pointX":512,"pointY":384},"width":1024,"sublayerTransform":[1,0,0,0,0,1,0,0,0,0,1,0,0,0,0,1],"contentsRect":{"y":0,"x":0,"width":1,"height":1},"opacity":1,"edgeAntialiasingMask":0,"height":768,"hidden":false,"anchorPoint":{"pointX":0.5,"pointY":0.5}},"texture":"03B001ED4B040174678FD2FC47A129FE"}]}]},"effects":[],"duration":0.01,"type":"transition","name":"none","objectID":"0"}],"automaticPlay":false,"hyperlinks":[],"accessibility":[{"text":"Language Prerequisites","targetRectangle":{"y":72,"x":86.63999999999999,"width":850.72,"height":96}},{"text":"Data centric","targetRectangle":{"y":211,"x":105.9499989652634,"width":150.9908399999999,"height":32}},{"text":"Collection literal syntax","targetRectangle":{"y":243,"x":140.9499989652634,"width":284.98932,"height":64.33999919891357}},{"text":"An API for manipulating pure data/data structures","targetRectangle":{"y":307.3399991989136,"x":140.9499989652634,"width":613.6930800000002,"height":64.33999919891357}},{"text":"Homoiconicity is a plus","targetRectangle":{"y":371.6799983978271,"x":140.9499989652634,"width":286.51392,"height":64.33999919891357}},{"text":"A functional language","targetRectangle":{"y":436.0199975967407,"x":105.9499989652634,"width":271.1847599999999,"height":64.33999919891357}},{"text":"First class and higher order functions","targetRectangle":{"y":500.3599967956543,"x":140.9499989652634,"width":460.1242800000001,"height":64.33999919891357}},{"text":"Referential transparency","targetRectangle":{"y":564.6999959945679,"x":140.9499989652634,"width":302.50836,"height":64.33999919891357}},{"text":"Immutability","targetRectangle":{"y":629.0399951934814,"x":140.9499989652634,"width":149.38308,"height":64.33999919891357}}],"baseLayer":{"animations":[],"initialState":{"affineTransform":[1,0,0,1,0,0],"masksToBounds":false,"rotation":0,"scale":1,"position":{"pointX":512,"pointY":384},"width":1024,"sublayerTransform":[1,0,0,0,0,1,0,0,0,0,1,0,0,0,0,1],"contentsRect":{"y":0,"x":0,"width":1,"height":1},"opacity":1,"edgeAntialiasingMask":251658240,"height":768,"hidden":false,"anchorPoint":{"pointX":0.5,"pointY":0.5}},"objectID":"0","layers":[{"animations":[],"initialState":{"affineTransform":[1,0,0,1,0,0],"masksToBounds":false,"rotation":0,"scale":1,"position":{"pointX":512,"pointY":384},"width":1024,"sublayerTransform":[1,0,0,0,0,1,0,0,0,0,1,-0.0004922987690640373,0,0,0,1],"contentsRect":{"y":0,"x":0,"width":1,"height":1},"opacity":1,"edgeAntialiasingMask":251658240,"height":768,"hidden":false,"anchorPoint":{"pointX":0.5,"pointY":0.5}},"layers":[{"animations":[],"layers":[],"initialState":{"affineTransform":[1,0,0,1,0,0],"masksToBounds":false,"rotation":0,"scale":1,"position":{"pointX":512,"pointY":384},"width":1024,"sublayerTransform":[1,0,0,0,0,1,0,0,0,0,1,0,0,0,0,1],"contentsRect":{"y":0,"x":0,"width":1,"height":1},"opacity":1,"edgeAntialiasingMask":0,"height":768,"hidden":false,"anchorPoint":{"pointX":0.5,"pointY":0.5}},"texture":"03B001ED4B040174678FD2FC47A129FE"}]}]}}]}