{"assets":{"B6E88BE885F363A186FA11D2EB9D36C7":{"type":"texture","index":131,"assetRequest":{"type":"slide","state":"contents","slide":"B8180DF4-B80F-4681-9E64-289C3A0357C6"},"url":{"web":"assets/B6E88BE885F363A186FA11D2EB9D36C7.svg"},"width":157,"height":27},"216079686484A9422527DCA5B057173E":{"type":"texture","index":133,"assetRequest":{"type":"slide","state":"incoming","slide":"885C4B7A-7F19-42E1-8158-3081FBB2FDCA"},"url":{"web":"assets/216079686484A9422527DCA5B057173E.svg"},"width":1024,"height":768},"242ED8EE4849FC8136DCF885474E04BD":{"type":"texture","index":130,"assetRequest":{"type":"slide","state":"contents","slide":"B8180DF4-B80F-4681-9E64-289C3A0357C6"},"url":{"web":"assets/242ED8EE4849FC8136DCF885474E04BD.svg"},"width":158,"height":26},"5949E544CCC52F524E9F72A253F93646":{"type":"texture","index":127,"assetRequest":{"type":"slide","state":"contents","slide":"B8180DF4-B80F-4681-9E64-289C3A0357C6"},"url":{"web":"assets/5949E544CCC52F524E9F72A253F93646.svg"},"width":1009,"height":491},"9E50FEF1936133F59FE5FF2684F6F33E":{"type":"texture","index":132,"assetRequest":{"type":"slide","state":"outgoing","slide":"B8180DF4-B80F-4681-9E64-289C3A0357C6"},"url":{"web":"assets/9E50FEF1936133F59FE5FF2684F6F33E.svg"},"width":1024,"height":768},"589AD146E0A9A84CBFFE256A491C5525":{"type":"texture","index":129,"assetRequest":{"type":"slide","state":"contents","slide":"B8180DF4-B80F-4681-9E64-289C3A0357C6"},"url":{"web":"assets/589AD146E0A9A84CBFFE256A491C5525.svg"},"width":270,"height":26},"170F5D53A47E1DE75AA53E7E84498798":{"type":"texture","index":128,"assetRequest":{"type":"slide","state":"contents","slide":"B8180DF4-B80F-4681-9E64-289C3A0357C6"},"url":{"web":"assets/170F5D53A47E1DE75AA53E7E84498798.svg"},"width":582,"height":51},"2C466DDB2FCA21520C2BCA135A82EA94":{"type":"texture","index":126,"assetRequest":{"type":"slide","state":"contents","slide":"B8180DF4-B80F-4681-9E64-289C3A0357C6"},"url":{"web":"assets/2C466DDB2FCA21520C2BCA135A82EA94.svg"},"width":260,"height":63},"498E23C82CA78A4BCD7BA88E5243B6FC":{"type":"texture","index":125,"assetRequest":{"type":"slide","state":"contents","slide":"B8180DF4-B80F-4681-9E64-289C3A0357C6"},"url":{"web":"assets/498E23C82CA78A4BCD7BA88E5243B6FC.svg"},"width":1024,"height":768}},"events":[{"effects":[{"beginTime":0,"baseLayer":{"animations":[],"initialState":{"affineTransform":[1,0,0,1,0,0],"masksToBounds":false,"rotation":0,"scale":1,"position":{"pointX":422.6002850532532,"pointY":276.0287190079689},"width":267.0376062393188,"sublayerTransform":[1,0,0,0,0,1,0,0,0,0,1,0,0,0,0,1],"contentsRect":{"y":0,"x":0,"width":1,"height":1},"opacity":1,"edgeAntialiasingMask":251658240,"height":23.83673489093781,"hidden":false,"anchorPoint":{"pointX":0.5,"pointY":0.5}},"objectID":"0ADE5258-12E8-437D-85B2-8750A582039D","layers":[{"animations":[],"initialState":{"affineTransform":[1,0,0,1,0,0],"masksToBounds":false,"rotation":0,"scale":1,"position":{"pointX":222.9185180664062,"pointY":119.8896484375},"width":267.0376062393188,"sublayerTransform":[1,0,0,0,0,1,0,0,0,0,1,-0.0004922987690640373,0,0,0,1],"contentsRect":{"y":0,"x":0,"width":1,"height":1},"opacity":1,"edgeAntialiasingMask":251658240,"height":23.83673489093781,"hidden":false,"anchorPoint":{"pointX":0.8347832397307624,"pointY":5.029617058965545}},"layers":[{"animations":[{"timeOffset":0,"from":{"scalar":true},"beginTime":1e-100,"repeatCount":0,"fillMode":"both","property":"hidden","autoreverses":false,"duration":0.01,"to":{"scalar":false}}],"layers":[],"initialState":{"affineTransform":[1,0,0,1,0,0],"masksToBounds":false,"rotation":0,"scale":1,"position":{"pointX":133.9185180664062,"pointY":11.8896484375},"width":270,"sublayerTransform":[1,0,0,0,0,1,0,0,0,0,1,0,0,0,0,1],"contentsRect":{"y":0,"x":0,"width":1,"height":1},"opacity":1,"edgeAntialiasingMask":0,"height":26,"hidden":true,"anchorPoint":{"pointX":0.5,"pointY":0.5}},"texture":"589AD146E0A9A84CBFFE256A491C5525"}]}]},"effects":[],"duration":0.01,"type":"buildIn","name":"apple:appear","objectID":"0ADE5258-12E8-437D-85B2-8750A582039D"},{"beginTime":0,"baseLayer":{"animations":[],"initialState":{"affineTransform":[1,0,0,1,0,0],"masksToBounds":false,"rotation":0,"scale":1,"position":{"pointX":395.2189772129059,"pointY":407.0169087052345},"width":154.8786282539368,"sublayerTransform":[1,0,0,0,0,1,0,0,0,0,1,0,0,0,0,1],"contentsRect":{"y":0,"x":0,"width":1,"height":1},"opacity":1,"edgeAntialiasingMask":251658240,"height":23.83673489093781,"hidden":false,"anchorPoint":{"pointX":0.5,"pointY":0.5}},"objectID":"5407C446-3036-4A5A-A015-3423BD57243A","layers":[{"animations":[],"initialState":{"affineTransform":[1,0,0,1,0,0],"masksToBounds":false,"rotation":0,"scale":1,"position":{"pointX":194.2203369140625,"pointY":-11.09854125976562},"width":154.8786282539368,"sublayerTransform":[1,0,0,0,0,1,0,0,0,0,1,-0.0004922987690640373,0,0,0,1],"contentsRect":{"y":0,"x":0,"width":1,"height":1},"opacity":1,"edgeAntialiasingMask":251658240,"height":23.83673489093781,"hidden":false,"anchorPoint":{"pointX":1.254016381108578,"pointY":-0.4656066072197264}},"layers":[{"animations":[{"timeOffset":0,"from":{"scalar":true},"beginTime":1e-100,"repeatCount":0,"fillMode":"both","property":"hidden","autoreverses":false,"duration":0.01,"to":{"scalar":false}}],"layers":[],"initialState":{"affineTransform":[1,0,0,1,0,0],"masksToBounds":false,"rotation":0,"scale":1,"position":{"pointX":77.2203369140625,"pointY":11.90145874023438},"width":158,"sublayerTransform":[1,0,0,0,0,1,0,0,0,0,1,0,0,0,0,1],"contentsRect":{"y":0,"x":0,"width":1,"height":1},"opacity":1,"edgeAntialiasingMask":0,"height":26,"hidden":true,"anchorPoint":{"pointX":0.5,"pointY":0.5}},"texture":"242ED8EE4849FC8136DCF885474E04BD"}]}]},"effects":[],"duration":0.01,"type":"buildIn","name":"apple:appear","objectID":"5407C446-3036-4A5A-A015-3423BD57243A"},{"beginTime":0,"baseLayer":{"animations":[],"initialState":{"affineTransform":[1,0,0,1,0,0],"masksToBounds":false,"rotation":0,"scale":1,"position":{"pointX":836.4767897129059,"pointY":484.8968830704689},"width":154.8786282539368,"sublayerTransform":[1,0,0,0,0,1,0,0,0,0,1,0,0,0,0,1],"contentsRect":{"y":0,"x":0,"width":1,"height":1},"opacity":1,"edgeAntialiasingMask":251658240,"height":23.83673489093781,"hidden":false,"anchorPoint":{"pointX":0.5,"pointY":0.5}},"objectID":"2B80938E-5196-4702-A2DE-C55EECCE6639","layers":[{"animations":[],"initialState":{"affineTransform":[1,0,0,1,0,0],"masksToBounds":false,"rotation":0,"scale":1,"position":{"pointX":-247.0374755859375,"pointY":-88.978515625},"width":154.8786282539368,"sublayerTransform":[1,0,0,0,0,1,0,0,0,0,1,-0.0004922987690640373,0,0,0,1],"contentsRect":{"y":0,"x":0,"width":1,"height":1},"opacity":1,"edgeAntialiasingMask":251658240,"height":23.83673489093781,"hidden":false,"anchorPoint":{"pointX":-1.595039150146,"pointY":-3.732831532175476}},"layers":[{"animations":[{"timeOffset":0,"from":{"scalar":true},"beginTime":1e-100,"repeatCount":0,"fillMode":"both","property":"hidden","autoreverses":false,"duration":0.01,"to":{"scalar":false}}],"layers":[],"initialState":{"affineTransform":[1,0,0,1,0,0],"masksToBounds":false,"rotation":0,"scale":1,"position":{"pointX":77.4625244140625,"pointY":11.521484375},"width":157,"sublayerTransform":[1,0,0,0,0,1,0,0,0,0,1,0,0,0,0,1],"contentsRect":{"y":0,"x":0,"width":1,"height":1},"opacity":1,"edgeAntialiasingMask":0,"height":27,"hidden":true,"anchorPoint":{"pointX":0.5,"pointY":0.5}},"texture":"B6E88BE885F363A186FA11D2EB9D36C7"}]}]},"effects":[],"duration":0.01,"type":"buildIn","name":"apple:appear","objectID":"2B80938E-5196-4702-A2DE-C55EECCE6639"}],"automaticPlay":false,"hyperlinks":[],"accessibility":[{"text":"Useful predicate functions","targetRectangle":{"y":149.5477752685547,"x":219.275,"width":585.45,"height":60}},{"text":"    1 (defn winner? [{ :keys [board] :as game-state }]","targetRectangle":{"y":236.9956865310669,"x":2.00001335144043,"width":745.3212890625,"height":26}},{"text":"    2   (let [color (active-player-color game-state)]","targetRectangle":{"y":262.9956865310669,"x":2.00001335144043,"width":731.51904296875,"height":26}},{"text":"    3     (-> board last :pieces color (= 6))))","targetRectangle":{"y":288.9956865310669,"x":2.00001335144043,"width":648.70556640625,"height":26}},{"text":"    4 ","targetRectangle":{"y":314.9956865310669,"x":2.00001335144043,"width":82.8134765625,"height":26}},{"text":"    5 (defn space-available? [board index]","targetRectangle":{"y":340.9956865310669,"x":2.00001335144043,"width":579.6943359375,"height":26}},{"text":"    6   (and (< index (count board))","targetRectangle":{"y":366.9956865310669,"x":2.00001335144043,"width":496.880859375,"height":26}},{"text":"    7        (< 0 (or (piece-count (:pieces (board index))) 0) 3)))","targetRectangle":{"y":392.9956865310669,"x":2.00001335144043,"width":924.75048828125,"height":26}},{"text":"    8 ","targetRectangle":{"y":418.9956865310669,"x":2.00001335144043,"width":82.8134765625,"height":26}},{"text":"    9 (defn space-occupied? [game-state index]","targetRectangle":{"y":444.9956865310669,"x":2.00001335144043,"width":634.9033203125,"height":26}},{"text":"   10   (-> game-state (get-in [:board index :pieces]) piece-count pos?))","targetRectangle":{"y":470.9956865310669,"x":2.00001335144043,"width":1007.56396484375,"height":26}},{"text":"   11 ","targetRectangle":{"y":496.9956865310669,"x":2.00001335144043,"width":82.8134765625,"height":26}},{"text":"   12 (defn player-has-card? [game-state card color]","targetRectangle":{"y":522.9956865310669,"x":2.00001335144043,"width":717.716796875,"height":26}},{"text":"   13   (pos? (get-in game-state [:players color :cards card])))","targetRectangle":{"y":548.9956865310669,"x":2.00001335144043,"width":883.34375,"height":26}},{"text":"   14 ","targetRectangle":{"y":574.9956865310669,"x":2.00001335144043,"width":82.8134765625,"height":26}},{"text":"   15 (defn square-has-color? [game-state color index]","targetRectangle":{"y":600.9956865310669,"x":2.00001335144043,"width":745.3212890625,"height":26}},{"text":"   16   (pos? (get-in game-state [:board index :pieces color])))","targetRectangle":{"y":626.9956865310669,"x":2.00001335144043,"width":883.34375,"height":26}},{"text":"   17 ","targetRectangle":{"y":652.9956865310669,"x":2.00001335144043,"width":82.8134765625,"height":26}},{"text":"   18 (defn players-turn? [game-state color]","targetRectangle":{"y":678.9956865310669,"x":2.00001335144043,"width":607.298828125,"height":26}},{"text":"   19   (pos? (get-in game-state [:players color :actions])))","targetRectangle":{"y":704.9956865310669,"x":2.00001335144043,"width":841.93701171875,"height":26}},{"text":"Queries","targetRectangle":{"y":40.09989166259766,"x":380.3624,"width":263.2752,"height":90}}],"baseLayer":{"animations":[],"initialState":{"affineTransform":[1,0,0,1,0,0],"masksToBounds":false,"rotation":0,"scale":1,"position":{"pointX":512,"pointY":384},"width":1024,"sublayerTransform":[1,0,0,0,0,1,0,0,0,0,1,0,0,0,0,1],"contentsRect":{"y":0,"x":0,"width":1,"height":1},"opacity":1,"edgeAntialiasingMask":251658240,"height":768,"hidden":false,"anchorPoint":{"pointX":0.5,"pointY":0.5}},"layers":[{"animations":[],"initialState":{"affineTransform":[1,0,0,1,0,0],"masksToBounds":false,"rotation":0,"scale":1,"position":{"pointX":512,"pointY":384},"width":1024,"sublayerTransform":[1,0,0,0,0,1,0,0,0,0,1,0,0,0,0,1],"contentsRect":{"y":0,"x":0,"width":1,"height":1},"opacity":1,"edgeAntialiasingMask":251658240,"height":768,"hidden":false,"anchorPoint":{"pointX":0.5,"pointY":0.5}},"layers":[{"animations":[],"initialState":{"affineTransform":[1,0,0,1,0,0],"masksToBounds":false,"rotation":0,"scale":1,"position":{"pointX":512,"pointY":384},"width":1024,"sublayerTransform":[1,0,0,0,0,1,0,0,0,0,1,0,0,0,0,1],"contentsRect":{"y":0,"x":0,"width":1,"height":1},"opacity":1,"edgeAntialiasingMask":251658240,"height":768,"hidden":false,"anchorPoint":{"pointX":0.5,"pointY":0.5}},"layers":[{"animations":[],"layers":[],"initialState":{"affineTransform":[1,0,0,1,0,0],"masksToBounds":false,"rotation":0,"scale":1,"position":{"pointX":512,"pointY":384},"width":1024,"sublayerTransform":[1,0,0,0,0,1,0,0,0,0,1,0,0,0,0,1],"contentsRect":{"y":0,"x":0,"width":1,"height":1},"opacity":1,"edgeAntialiasingMask":0,"height":768,"hidden":false,"anchorPoint":{"pointX":0.5,"pointY":0.5}},"texture":"498E23C82CA78A4BCD7BA88E5243B6FC"}]}]},{"animations":[],"initialState":{"affineTransform":[1,0,0,1,0,0],"masksToBounds":false,"rotation":0,"scale":1,"position":{"pointX":512,"pointY":384},"width":1024,"sublayerTransform":[1,0,0,0,0,1,0,0,0,0,1,0,0,0,0,1],"contentsRect":{"y":0,"x":0,"width":1,"height":1},"opacity":1,"edgeAntialiasingMask":251658240,"height":768,"hidden":false,"anchorPoint":{"pointX":0.5,"pointY":0.5}},"layers":[{"animations":[],"initialState":{"affineTransform":[1,0,0,1,0,0],"masksToBounds":false,"rotation":0,"scale":1,"position":{"pointX":512,"pointY":84.88292038440704},"width":874,"sublayerTransform":[1,0,0,0,0,1,0,0,0,0,1,0,0,0,0,1],"contentsRect":{"y":0,"x":0,"width":1,"height":1},"opacity":1,"edgeAntialiasingMask":251658240,"height":97.56605744361877,"hidden":false,"anchorPoint":{"pointX":0.5,"pointY":0.5}},"objectID":"8898AAA8-062E-4730-93F7-EA84CDE6D5C7","layers":[{"animations":[],"layers":[],"initialState":{"affineTransform":[1,0,0,1,0,0],"masksToBounds":false,"rotation":0,"scale":1,"position":{"pointX":437,"pointY":51.40010833740234},"width":260,"sublayerTransform":[1,0,0,0,0,1,0,0,0,0,1,0,0,0,0,1],"contentsRect":{"y":0,"x":0,"width":1,"height":1},"opacity":1,"edgeAntialiasingMask":0,"height":63,"hidden":false,"anchorPoint":{"pointX":0.5,"pointY":0.5}},"texture":"2C466DDB2FCA21520C2BCA135A82EA94"}]}]},{"animations":[],"initialState":{"affineTransform":[1,0,0,1,0,0],"masksToBounds":false,"rotation":0,"scale":1,"position":{"pointX":512,"pointY":384},"width":1024,"sublayerTransform":[1,0,0,0,0,1,0,0,0,0,1,0,0,0,0,1],"contentsRect":{"y":0,"x":0,"width":1,"height":1},"opacity":1,"edgeAntialiasingMask":251658240,"height":768,"hidden":false,"anchorPoint":{"pointX":0.5,"pointY":0.5}},"layers":[{"animations":[],"initialState":{"affineTransform":[1,0,0,1,0,0],"masksToBounds":false,"rotation":0,"scale":1,"position":{"pointX":512,"pointY":496.9956970214844},"width":1027.999973297119,"sublayerTransform":[1,0,0,0,0,1,0,0,0,0,1,0,0,0,0,1],"contentsRect":{"y":0,"x":0,"width":1,"height":1},"opacity":1,"edgeAntialiasingMask":251658240,"height":528.000020980835,"hidden":false,"anchorPoint":{"pointX":0.5,"pointY":0.5}},"objectID":"10AE7E5D-4193-4BD5-9B52-81861521CEED","layers":[{"animations":[],"layers":[],"initialState":{"affineTransform":[1,0,0,1,0,0],"masksToBounds":false,"rotation":0,"scale":1,"position":{"pointX":507.4999866485596,"pointY":251.5043134689331},"width":1009,"sublayerTransform":[1,0,0,0,0,1,0,0,0,0,1,0,0,0,0,1],"contentsRect":{"y":0,"x":0,"width":1,"height":1},"opacity":1,"edgeAntialiasingMask":0,"height":491,"hidden":false,"anchorPoint":{"pointX":0.5,"pointY":0.5}},"texture":"5949E544CCC52F524E9F72A253F93646"}]}]},{"animations":[],"initialState":{"affineTransform":[1,0,0,1,0,0],"masksToBounds":false,"rotation":0,"scale":1,"position":{"pointX":512,"pointY":384},"width":1024,"sublayerTransform":[1,0,0,0,0,1,0,0,0,0,1,0,0,0,0,1],"contentsRect":{"y":0,"x":0,"width":1,"height":1},"opacity":1,"edgeAntialiasingMask":251658240,"height":768,"hidden":false,"anchorPoint":{"pointX":0.5,"pointY":0.5}},"layers":[{"animations":[],"initialState":{"affineTransform":[1,0,0,1,0,0],"masksToBounds":false,"rotation":0,"scale":1,"position":{"pointX":512,"pointY":179.3308039903641},"width":874,"sublayerTransform":[1,0,0,0,0,1,0,0,0,0,1,0,0,0,0,1],"contentsRect":{"y":0,"x":0,"width":1,"height":1},"opacity":1,"edgeAntialiasingMask":251658240,"height":97.56605744361877,"hidden":false,"anchorPoint":{"pointX":0.5,"pointY":0.5}},"objectID":"05074095-27E2-4B01-A883-6BF590C36C31","layers":[{"animations":[],"layers":[],"initialState":{"affineTransform":[1,0,0,1,0,0],"masksToBounds":false,"rotation":0,"scale":1,"position":{"pointX":438,"pointY":53.95222473144531},"width":582,"sublayerTransform":[1,0,0,0,0,1,0,0,0,0,1,0,0,0,0,1],"contentsRect":{"y":0,"x":0,"width":1,"height":1},"opacity":1,"edgeAntialiasingMask":0,"height":51,"hidden":false,"anchorPoint":{"pointX":0.5,"pointY":0.5}},"texture":"170F5D53A47E1DE75AA53E7E84498798"}]}]},{"animations":[],"initialState":{"affineTransform":[1,0,0,1,0,0],"masksToBounds":false,"rotation":0,"scale":1,"position":{"pointX":512,"pointY":384},"width":1024,"sublayerTransform":[1,0,0,0,0,1,0,0,0,0,1,0,0,0,0,1],"contentsRect":{"y":0,"x":0,"width":1,"height":1},"opacity":1,"edgeAntialiasingMask":251658240,"height":768,"hidden":false,"anchorPoint":{"pointX":0.5,"pointY":0.5}},"layers":[{"animations":[],"initialState":{"affineTransform":[1,0,0,1,0,0],"masksToBounds":false,"rotation":0,"scale":1,"position":{"pointX":422.6002850532532,"pointY":276.0287190079689},"width":267.0376062393188,"sublayerTransform":[1,0,0,0,0,1,0,0,0,0,1,0,0,0,0,1],"contentsRect":{"y":0,"x":0,"width":1,"height":1},"opacity":1,"edgeAntialiasingMask":251658240,"height":23.83673489093781,"hidden":false,"anchorPoint":{"pointX":0.5,"pointY":0.5}},"objectID":"0ADE5258-12E8-437D-85B2-8750A582039D","layers":[{"animations":[],"layers":[],"initialState":{"affineTransform":[1,0,0,1,0,0],"masksToBounds":false,"rotation":0,"scale":1,"position":{"pointX":133.9185180664062,"pointY":11.8896484375},"width":270,"sublayerTransform":[1,0,0,0,0,1,0,0,0,0,1,0,0,0,0,1],"contentsRect":{"y":0,"x":0,"width":1,"height":1},"opacity":1,"edgeAntialiasingMask":0,"height":26,"hidden":true,"anchorPoint":{"pointX":0.5,"pointY":0.5}},"texture":"589AD146E0A9A84CBFFE256A491C5525"}]}]},{"animations":[],"initialState":{"affineTransform":[1,0,0,1,0,0],"masksToBounds":false,"rotation":0,"scale":1,"position":{"pointX":512,"pointY":384},"width":1024,"sublayerTransform":[1,0,0,0,0,1,0,0,0,0,1,0,0,0,0,1],"contentsRect":{"y":0,"x":0,"width":1,"height":1},"opacity":1,"edgeAntialiasingMask":251658240,"height":768,"hidden":false,"anchorPoint":{"pointX":0.5,"pointY":0.5}},"layers":[{"animations":[],"initialState":{"affineTransform":[1,0,0,1,0,0],"masksToBounds":false,"rotation":0,"scale":1,"position":{"pointX":395.2189772129059,"pointY":407.0169087052345},"width":154.8786282539368,"sublayerTransform":[1,0,0,0,0,1,0,0,0,0,1,0,0,0,0,1],"contentsRect":{"y":0,"x":0,"width":1,"height":1},"opacity":1,"edgeAntialiasingMask":251658240,"height":23.83673489093781,"hidden":false,"anchorPoint":{"pointX":0.5,"pointY":0.5}},"objectID":"5407C446-3036-4A5A-A015-3423BD57243A","layers":[{"animations":[],"layers":[],"initialState":{"affineTransform":[1,0,0,1,0,0],"masksToBounds":false,"rotation":0,"scale":1,"position":{"pointX":77.2203369140625,"pointY":11.90145874023438},"width":158,"sublayerTransform":[1,0,0,0,0,1,0,0,0,0,1,0,0,0,0,1],"contentsRect":{"y":0,"x":0,"width":1,"height":1},"opacity":1,"edgeAntialiasingMask":0,"height":26,"hidden":true,"anchorPoint":{"pointX":0.5,"pointY":0.5}},"texture":"242ED8EE4849FC8136DCF885474E04BD"}]}]},{"animations":[],"initialState":{"affineTransform":[1,0,0,1,0,0],"masksToBounds":false,"rotation":0,"scale":1,"position":{"pointX":512,"pointY":384},"width":1024,"sublayerTransform":[1,0,0,0,0,1,0,0,0,0,1,0,0,0,0,1],"contentsRect":{"y":0,"x":0,"width":1,"height":1},"opacity":1,"edgeAntialiasingMask":251658240,"height":768,"hidden":false,"anchorPoint":{"pointX":0.5,"pointY":0.5}},"layers":[{"animations":[],"initialState":{"affineTransform":[1,0,0,1,0,0],"masksToBounds":false,"rotation":0,"scale":1,"position":{"pointX":836.4767897129059,"pointY":484.8968830704689},"width":154.8786282539368,"sublayerTransform":[1,0,0,0,0,1,0,0,0,0,1,0,0,0,0,1],"contentsRect":{"y":0,"x":0,"width":1,"height":1},"opacity":1,"edgeAntialiasingMask":251658240,"height":23.83673489093781,"hidden":false,"anchorPoint":{"pointX":0.5,"pointY":0.5}},"objectID":"2B80938E-5196-4702-A2DE-C55EECCE6639","layers":[{"animations":[],"layers":[],"initialState":{"affineTransform":[1,0,0,1,0,0],"masksToBounds":false,"rotation":0,"scale":1,"position":{"pointX":77.4625244140625,"pointY":11.521484375},"width":157,"sublayerTransform":[1,0,0,0,0,1,0,0,0,0,1,0,0,0,0,1],"contentsRect":{"y":0,"x":0,"width":1,"height":1},"opacity":1,"edgeAntialiasingMask":0,"height":27,"hidden":true,"anchorPoint":{"pointX":0.5,"pointY":0.5}},"texture":"B6E88BE885F363A186FA11D2EB9D36C7"}]}]}]}},{"effects":[{"beginTime":0,"baseLayer":{"animations":[],"initialState":{"affineTransform":[1,0,0,1,0,0],"masksToBounds":false,"rotation":0,"scale":1,"position":{"pointX":512,"pointY":384},"width":1024,"sublayerTransform":[1,0,0,0,0,1,0,0,0,0,1,0,0,0,0,1],"contentsRect":{"y":0,"x":0,"width":1,"height":1},"opacity":1,"edgeAntialiasingMask":251658240,"height":768,"hidden":false,"anchorPoint":{"pointX":0.5,"pointY":0.5}},"objectID":"0","layers":[{"animations":[],"initialState":{"affineTransform":[1,0,0,1,0,0],"masksToBounds":false,"rotation":0,"scale":1,"position":{"pointX":512,"pointY":384},"width":1024,"sublayerTransform":[1,0,0,0,0,1,0,0,0,0,1,-0.0004922987690640373,0,0,0,1],"contentsRect":{"y":0,"x":0,"width":1,"height":1},"opacity":1,"edgeAntialiasingMask":251658240,"height":768,"hidden":false,"anchorPoint":{"pointX":0.5,"pointY":0.5}},"layers":[{"animations":[],"layers":[],"initialState":{"affineTransform":[1,0,0,1,0,0],"masksToBounds":false,"rotation":0,"scale":1,"position":{"pointX":512,"pointY":384},"width":1024,"sublayerTransform":[1,0,0,0,0,1,0,0,0,0,1,0,0,0,0,1],"contentsRect":{"y":0,"x":0,"width":1,"height":1},"opacity":1,"edgeAntialiasingMask":0,"height":768,"hidden":false,"anchorPoint":{"pointX":0.5,"pointY":0.5}},"texture":"216079686484A9422527DCA5B057173E"},{"animations":[{"timeOffset":0,"from":{"scalar":false},"beginTime":0,"repeatCount":0,"fillMode":"both","property":"hidden","autoreverses":false,"duration":0.01,"to":{"scalar":true}}],"layers":[],"initialState":{"affineTransform":[1,0,0,1,0,0],"masksToBounds":false,"rotation":0,"scale":1,"position":{"pointX":512,"pointY":384},"width":1024,"sublayerTransform":[1,0,0,0,0,1,0,0,0,0,1,0,0,0,0,1],"contentsRect":{"y":0,"x":0,"width":1,"height":1},"opacity":1,"edgeAntialiasingMask":0,"height":768,"hidden":false,"anchorPoint":{"pointX":0.5,"pointY":0.5}},"texture":"9E50FEF1936133F59FE5FF2684F6F33E"}]}]},"effects":[],"duration":0.01,"type":"transition","name":"none","objectID":"0"}],"automaticPlay":false,"hyperlinks":[],"accessibility":[{"text":"Useful predicate functions","targetRectangle":{"y":149.5477752685547,"x":219.275,"width":585.45,"height":60}},{"text":"    1 (defn winner? [{ :keys [board] :as game-state }]","targetRectangle":{"y":236.9956865310669,"x":2.00001335144043,"width":745.3212890625,"height":26}},{"text":"    2   (let [color (active-player-color game-state)]","targetRectangle":{"y":262.9956865310669,"x":2.00001335144043,"width":731.51904296875,"height":26}},{"text":"    3     (-> board last :pieces color (= 6))))","targetRectangle":{"y":288.9956865310669,"x":2.00001335144043,"width":648.70556640625,"height":26}},{"text":"    4 ","targetRectangle":{"y":314.9956865310669,"x":2.00001335144043,"width":82.8134765625,"height":26}},{"text":"    5 (defn space-available? [board index]","targetRectangle":{"y":340.9956865310669,"x":2.00001335144043,"width":579.6943359375,"height":26}},{"text":"    6   (and (< index (count board))","targetRectangle":{"y":366.9956865310669,"x":2.00001335144043,"width":496.880859375,"height":26}},{"text":"    7        (< 0 (or (piece-count (:pieces (board index))) 0) 3)))","targetRectangle":{"y":392.9956865310669,"x":2.00001335144043,"width":924.75048828125,"height":26}},{"text":"    8 ","targetRectangle":{"y":418.9956865310669,"x":2.00001335144043,"width":82.8134765625,"height":26}},{"text":"    9 (defn space-occupied? [game-state index]","targetRectangle":{"y":444.9956865310669,"x":2.00001335144043,"width":634.9033203125,"height":26}},{"text":"   10   (-> game-state (get-in [:board index :pieces]) piece-count pos?))","targetRectangle":{"y":470.9956865310669,"x":2.00001335144043,"width":1007.56396484375,"height":26}},{"text":"   11 ","targetRectangle":{"y":496.9956865310669,"x":2.00001335144043,"width":82.8134765625,"height":26}},{"text":"   12 (defn player-has-card? [game-state card color]","targetRectangle":{"y":522.9956865310669,"x":2.00001335144043,"width":717.716796875,"height":26}},{"text":"   13   (pos? (get-in game-state [:players color :cards card])))","targetRectangle":{"y":548.9956865310669,"x":2.00001335144043,"width":883.34375,"height":26}},{"text":"   14 ","targetRectangle":{"y":574.9956865310669,"x":2.00001335144043,"width":82.8134765625,"height":26}},{"text":"   15 (defn square-has-color? [game-state color index]","targetRectangle":{"y":600.9956865310669,"x":2.00001335144043,"width":745.3212890625,"height":26}},{"text":"   16   (pos? (get-in game-state [:board index :pieces color])))","targetRectangle":{"y":626.9956865310669,"x":2.00001335144043,"width":883.34375,"height":26}},{"text":"   17 ","targetRectangle":{"y":652.9956865310669,"x":2.00001335144043,"width":82.8134765625,"height":26}},{"text":"   18 (defn players-turn? [game-state color]","targetRectangle":{"y":678.9956865310669,"x":2.00001335144043,"width":607.298828125,"height":26}},{"text":"   19   (pos? (get-in game-state [:players color :actions])))","targetRectangle":{"y":704.9956865310669,"x":2.00001335144043,"width":841.93701171875,"height":26}},{"text":"Queries","targetRectangle":{"y":40.09989166259766,"x":380.3624,"width":263.2752,"height":90}}],"baseLayer":{"animations":[],"initialState":{"affineTransform":[1,0,0,1,0,0],"masksToBounds":false,"rotation":0,"scale":1,"position":{"pointX":512,"pointY":384},"width":1024,"sublayerTransform":[1,0,0,0,0,1,0,0,0,0,1,0,0,0,0,1],"contentsRect":{"y":0,"x":0,"width":1,"height":1},"opacity":1,"edgeAntialiasingMask":251658240,"height":768,"hidden":false,"anchorPoint":{"pointX":0.5,"pointY":0.5}},"objectID":"0","layers":[{"animations":[],"initialState":{"affineTransform":[1,0,0,1,0,0],"masksToBounds":false,"rotation":0,"scale":1,"position":{"pointX":512,"pointY":384},"width":1024,"sublayerTransform":[1,0,0,0,0,1,0,0,0,0,1,-0.0004922987690640373,0,0,0,1],"contentsRect":{"y":0,"x":0,"width":1,"height":1},"opacity":1,"edgeAntialiasingMask":251658240,"height":768,"hidden":false,"anchorPoint":{"pointX":0.5,"pointY":0.5}},"layers":[{"animations":[],"layers":[],"initialState":{"affineTransform":[1,0,0,1,0,0],"masksToBounds":false,"rotation":0,"scale":1,"position":{"pointX":512,"pointY":384},"width":1024,"sublayerTransform":[1,0,0,0,0,1,0,0,0,0,1,0,0,0,0,1],"contentsRect":{"y":0,"x":0,"width":1,"height":1},"opacity":1,"edgeAntialiasingMask":0,"height":768,"hidden":false,"anchorPoint":{"pointX":0.5,"pointY":0.5}},"texture":"9E50FEF1936133F59FE5FF2684F6F33E"}]}]}}]}